pretty_progress/__init__.py
pretty_progress/pretty_progress.py
pretty_progress-0.1.4.dist-info/LICENCE
pretty_progress-0.1.4.dist-info/METADATA
pretty_progress-0.1.4.dist-info/WHEEL
pretty_progress-0.1.4.dist-info/top_level.txt
pretty_progress-0.1.4.dist-info/RECORD
