Metadata-Version: 2.1
Name: pretty_progress
Version: 0.1.4
Summary: A Python module for creating a terminal progress bar.
Author-email: Hal Kolb <hal@kolb.com>
License: MIT License
Project-URL: homepage, https://github.com/hal609/pretty-progress
Project-URL: repository, https://github.com/hal609/pretty-progress
Project-URL: bug-tracker, https://github.com/hal609/pretty-progress/issues
Keywords: progress bar,terminal,progress,python
Classifier: Programming Language :: Python :: 3
Classifier: License :: OSI Approved :: MIT License
Classifier: Operating System :: OS Independent
Requires-Python: >=3.6
License-File: LICENCE
